pack/__init__.py
ip_location_api-1.0.1.dist-info/entry_points.txt
ip_location_api-1.0.1.dist-info/WHEEL
ip_location_api-1.0.1.dist-info/METADATA
ip_location_api-1.0.1.dist-info/RECORD
