Metadata-Version: 2.1
Name: ip-location-api
Version: 1.0.1
Summary: Free IP Geolocation API and IP Location Lookup Database by https://ipwhois.io
Home-page: https://ipwhois.io/
Author: ipwhois.io
Requires-Python: ==2.7.5
Classifier: Programming Language :: Python :: 2
Project-URL: Documentation, https://ipwhois.io/documentation
